gaussbean/__init__.py
gaussbean/analysis/__init__.py
gaussbean/analysis/dataset.py
gaussbean/analysis/single.py
gaussbean/utils/__init__.py
gaussbean/utils/calc_utils.py
gaussbean/utils/plot_utils.py
gaussbean/utils/pre_utils.py
gaussbean-1.0.8.dist-info/LICENSE.txt
gaussbean-1.0.8.dist-info/METADATA
gaussbean-1.0.8.dist-info/WHEEL
gaussbean-1.0.8.dist-info/top_level.txt
gaussbean-1.0.8.dist-info/RECORD
