Metadata-Version: 2.1
Name: gaussbean
Version: 1.0.8
Summary: GAUSSian BEam ANalysis package
Author: Leah Hartman
Author-email: <leah.ghartman@gmail.com>
Keywords: python,gaussian,laser
License-File: LICENSE.txt
